cchloader/__init__.py
cchloader/compress.py
cchloader/exceptions.py
cchloader/file.py
cchloader/logging.py
cchloader/monkeypatch_libs.py
cchloader/monkeypatch_loader.py
cchloader/utils.py
cchloader/adapters/__init__.py
cchloader/adapters/a5d.py
cchloader/adapters/b5d.py
cchloader/adapters/corbagen.py
cchloader/adapters/f1.py
cchloader/adapters/f5d.py
cchloader/adapters/infpa.py
cchloader/adapters/mcilqh.py
cchloader/adapters/medidas.py
cchloader/adapters/mhcil.py
cchloader/adapters/p1.py
cchloader/adapters/p2.py
cchloader/adapters/p5d.py
cchloader/adapters/reganecu.py
cchloader/adapters/reganecuqh.py
cchloader/backends/__init__.py
cchloader/backends/base.py
cchloader/backends/mongodb.py
cchloader/backends/timescaledb.py
cchloader/cli/__init__.py
cchloader/models/__init__.py
cchloader/models/cch_autocons.py
cchloader/models/cch_gennetabeta.py
cchloader/models/cchfact.py
cchloader/models/cchval.py
cchloader/models/corbagen.py
cchloader/models/f1.py
cchloader/models/infpa.py
cchloader/models/mcilqh.py
cchloader/models/medidas.py
cchloader/models/mhcil.py
cchloader/models/p1.py
cchloader/models/reganecu.py
cchloader/models/reganecuqh.py
cchloader/parsers/__init__.py
cchloader/parsers/a5d.py
cchloader/parsers/b5d.py
cchloader/parsers/corbagen.py
cchloader/parsers/f1.py
cchloader/parsers/f5d.py
cchloader/parsers/infpa.py
cchloader/parsers/mcilqh.py
cchloader/parsers/medidas.py
cchloader/parsers/mhcil.py
cchloader/parsers/p1.py
cchloader/parsers/p1d.py
cchloader/parsers/p2.py
cchloader/parsers/p2d.py
cchloader/parsers/p5d.py
cchloader/parsers/parser.py
cchloader/parsers/reganecu.py
cchloader/parsers/reganecuqh.py
cchloader/parsers/rf5d.py
cchloader-4.0.0.dist-info/licenses/LICENSE
tests/__init__.py
cchloader-4.0.0.dist-info/METADATA
cchloader-4.0.0.dist-info/WHEEL
cchloader-4.0.0.dist-info/entry_points.txt
cchloader-4.0.0.dist-info/top_level.txt
cchloader-4.0.0.dist-info/RECORD
